ai_sub/__init__.py
ai_sub/agent_wrapper.py
ai_sub/config.py
ai_sub/data_models.py
ai_sub/gemini_cli_wrapper.py
ai_sub/gemini_file_uploader.py
ai_sub/job_runner.py
ai_sub/main.py
ai_sub/prompt.py
ai_sub/video.py
ai_sub-1.9.1.dist-info/licenses/LICENSE
ai_sub-1.9.1.dist-info/METADATA
ai_sub-1.9.1.dist-info/WHEEL
ai_sub-1.9.1.dist-info/entry_points.txt
ai_sub-1.9.1.dist-info/top_level.txt
ai_sub-1.9.1.dist-info/RECORD
