Metadata-Version: 2.4
Name: ai-sub
Version: 1.9.1
Summary: AI-Powered Subtitle Generation with Translation
Author: FlippFuzz
Project-URL: Homepage, https://github.com/FlippFuzz/ai-sub
Project-URL: Bug Tracker, https://github.com/FlippFuzz/ai-sub/issues
Requires-Python: >=3.10
License-File: LICENSE
Requires-Dist: pysubs2
Requires-Dist: static-ffmpeg
Requires-Dist: pydantic
Requires-Dist: pydantic-ai-slim[google,logfire]
Requires-Dist: pydantic-settings
Requires-Dist: json_repair
Requires-Dist: pyrate-limiter
Dynamic: license-file
